{"admin":{"listen":"tcp/localhost:2019"},"apps":{"crowdsec":{"api_key":"7Z2pbq4gu/EragIQybaU8LlnyeqslowQhNnnB/6BeLU","api_url":"http://crowdsec:8080/","appsec_url":"http://crowdsec:7422","enable_hard_fails":false,"enable_streaming":true,"ticker_interval":"60s"},"http":{"servers":{"srv0":{"client_ip_headers":["X-Forwarded-For","X-Real-IP"],"listen":[":443"],"logs":{"logger_names":{"*.bitsonline":["log0"],"*.indehoven.com":["log1"],"aliasvault.indehoven.com":["log2"],"bitsonline.nl":["log0"],"dns.indehoven.com":["log5"],"dockhand.indehoven.com":["log6"],"dozzle.indehoven.com":["log7"],"id.indehoven.com":["log3"],"indehoven.com":["log1"],"monitor.indehoven.com":["log4"],"portainer.indehoven.com":["log8"],"vaultwarden.indehoven.com":["log9"],"zerobyte.indehoven.com":["log10"]}},"routes":[{"handle":[{"handler":"subroute","routes":[{"handle":[{"handler":"subroute","routes":[{"handle":[{"handler":"crowdsec"},{"handler":"appsec"}]},{"handle":[{"handler":"reverse_proxy","upstreams":[{"dial":"authentik-server:9000"}]}],"match":[{"path":["/outpost.goauthentik.io/*"]}]},{"handle":[{"handle_response":[{"match":{"status_code":[2]},"routes":[{"handle":[{"handler":"vars"}]},{"handle":[{"handler":"headers","request":{"delete":["X-Authentik-Email"]}}]},{"handle":[{"handler":"headers","request":{"set":{"X-Authentik-Email":["{http.reverse_proxy.header.X-Authentik-Email}"]}}}],"match":[{"not":[{"vars":{"{http.reverse_proxy.header.X-Authentik-Email}":[""]}}]}]},{"handle":[{"handler":"headers","request":{"delete":["X-Authentik-Groups"]}}]},{"handle":[{"handler":"headers","request":{"set":{"X-Authentik-Groups":["{http.reverse_proxy.header.X-Authentik-Groups}"]}}}],"match":[{"not":[{"vars":{"{http.reverse_proxy.header.X-Authentik-Groups}":[""]}}]}]},{"handle":[{"handler":"headers","request":{"delete":["X-Authentik-Jwt"]}}]},{"handle":[{"handler":"headers","request":{"set":{"X-Authentik-Jwt":["{http.reverse_proxy.header.X-Authentik-Jwt}"]}}}],"match":[{"not":[{"vars":{"{http.reverse_proxy.header.X-Authentik-Jwt}":[""]}}]}]},{"handle":[{"handler":"headers","request":{"delete":["X-Authentik-Name"]}}]},{"handle":[{"handler":"headers","request":{"set":{"X-Authentik-Name":["{http.reverse_proxy.header.X-Authentik-Name}"]}}}],"match":[{"not":[{"vars":{"{http.reverse_proxy.header.X-Authentik-Name}":[""]}}]}]},{"handle":[{"handler":"headers","request":{"delete":["X-Authentik-Uid"]}}]},{"handle":[{"handler":"headers","request":{"set":{"X-Authentik-Uid":["{http.reverse_proxy.header.X-Authentik-Uid}"]}}}],"match":[{"not":[{"vars":{"{http.reverse_proxy.header.X-Authentik-Uid}":[""]}}]}]},{"handle":[{"handler":"headers","request":{"delete":["X-Authentik-Username"]}}]},{"handle":[{"handler":"headers","request":{"set":{"X-Authentik-Username":["{http.reverse_proxy.header.X-Authentik-Username}"]}}}],"match":[{"not":[{"vars":{"{http.reverse_proxy.header.X-Authentik-Username}":[""]}}]}]}]}],"handler":"reverse_proxy","headers":{"request":{"set":{"X-Forwarded-Method":["{http.request.method}"],"X-Forwarded-Uri":["{http.request.uri}"]}}},"rewrite":{"method":"GET","uri":"/outpost.goauthentik.io/auth/caddy"},"upstreams":[{"dial":"authentik-server:9000"}]},{"handler":"reverse_proxy","upstreams":[{"dial":"vaultwarden:80"}]}]}]}]}]}],"match":[{"host":["vaultwarden.indehoven.com"]}],"terminal":true},{"handle":[{"handler":"subroute","routes":[{"handle":[{"handler":"subroute","routes":[{"handle":[{"handler":"crowdsec"},{"handler":"appsec"}]},{"handle":[{"handler":"reverse_proxy","upstreams":[{"dial":"authentik-server:9000"}]}],"match":[{"path":["/outpost.goauthentik.io/*"]}]},{"handle":[{"handle_response":[{"match":{"status_code":[2]},"routes":[{"handle":[{"handler":"vars"}]},{"handle":[{"handler":"headers","request":{"delete":["X-Authentik-Email"]}}]},{"handle":[{"handler":"headers","request":{"set":{"X-Authentik-Email":["{http.reverse_proxy.header.X-Authentik-Email}"]}}}],"match":[{"not":[{"vars":{"{http.reverse_proxy.header.X-Authentik-Email}":[""]}}]}]},{"handle":[{"handler":"headers","request":{"delete":["X-Authentik-Groups"]}}]},{"handle":[{"handler":"headers","request":{"set":{"X-Authentik-Groups":["{http.reverse_proxy.header.X-Authentik-Groups}"]}}}],"match":[{"not":[{"vars":{"{http.reverse_proxy.header.X-Authentik-Groups}":[""]}}]}]},{"handle":[{"handler":"headers","request":{"delete":["X-Authentik-Jwt"]}}]},{"handle":[{"handler":"headers","request":{"set":{"X-Authentik-Jwt":["{http.reverse_proxy.header.X-Authentik-Jwt}"]}}}],"match":[{"not":[{"vars":{"{http.reverse_proxy.header.X-Authentik-Jwt}":[""]}}]}]},{"handle":[{"handler":"headers","request":{"delete":["X-Authentik-Name"]}}]},{"handle":[{"handler":"headers","request":{"set":{"X-Authentik-Name":["{http.reverse_proxy.header.X-Authentik-Name}"]}}}],"match":[{"not":[{"vars":{"{http.reverse_proxy.header.X-Authentik-Name}":[""]}}]}]},{"handle":[{"handler":"headers","request":{"delete":["X-Authentik-Uid"]}}]},{"handle":[{"handler":"headers","request":{"set":{"X-Authentik-Uid":["{http.reverse_proxy.header.X-Authentik-Uid}"]}}}],"match":[{"not":[{"vars":{"{http.reverse_proxy.header.X-Authentik-Uid}":[""]}}]}]},{"handle":[{"handler":"headers","request":{"delete":["X-Authentik-Username"]}}]},{"handle":[{"handler":"headers","request":{"set":{"X-Authentik-Username":["{http.reverse_proxy.header.X-Authentik-Username}"]}}}],"match":[{"not":[{"vars":{"{http.reverse_proxy.header.X-Authentik-Username}":[""]}}]}]}]}],"handler":"reverse_proxy","headers":{"request":{"set":{"X-Forwarded-Method":["{http.request.method}"],"X-Forwarded-Uri":["{http.request.uri}"]}}},"rewrite":{"method":"GET","uri":"/outpost.goauthentik.io/auth/caddy"},"upstreams":[{"dial":"authentik-server:9000"}]},{"handler":"reverse_proxy","upstreams":[{"dial":"aliasvault:80"}]}]}]}]}]}],"match":[{"host":["aliasvault.indehoven.com"]}],"terminal":true},{"handle":[{"handler":"subroute","routes":[{"handle":[{"handler":"subroute","routes":[{"handle":[{"handler":"crowdsec"},{"handler":"appsec"}]},{"handle":[{"handler":"reverse_proxy","upstreams":[{"dial":"authentik-server:9000"}]}],"match":[{"path":["/outpost.goauthentik.io/*"]}]},{"handle":[{"handle_response":[{"match":{"status_code":[2]},"routes":[{"handle":[{"handler":"vars"}]},{"handle":[{"handler":"headers","request":{"delete":["X-Authentik-Email"]}}]},{"handle":[{"handler":"headers","request":{"set":{"X-Authentik-Email":["{http.reverse_proxy.header.X-Authentik-Email}"]}}}],"match":[{"not":[{"vars":{"{http.reverse_proxy.header.X-Authentik-Email}":[""]}}]}]},{"handle":[{"handler":"headers","request":{"delete":["X-Authentik-Groups"]}}]},{"handle":[{"handler":"headers","request":{"set":{"X-Authentik-Groups":["{http.reverse_proxy.header.X-Authentik-Groups}"]}}}],"match":[{"not":[{"vars":{"{http.reverse_proxy.header.X-Authentik-Groups}":[""]}}]}]},{"handle":[{"handler":"headers","request":{"delete":["X-Authentik-Jwt"]}}]},{"handle":[{"handler":"headers","request":{"set":{"X-Authentik-Jwt":["{http.reverse_proxy.header.X-Authentik-Jwt}"]}}}],"match":[{"not":[{"vars":{"{http.reverse_proxy.header.X-Authentik-Jwt}":[""]}}]}]},{"handle":[{"handler":"headers","request":{"delete":["X-Authentik-Name"]}}]},{"handle":[{"handler":"headers","request":{"set":{"X-Authentik-Name":["{http.reverse_proxy.header.X-Authentik-Name}"]}}}],"match":[{"not":[{"vars":{"{http.reverse_proxy.header.X-Authentik-Name}":[""]}}]}]},{"handle":[{"handler":"headers","request":{"delete":["X-Authentik-Uid"]}}]},{"handle":[{"handler":"headers","request":{"set":{"X-Authentik-Uid":["{http.reverse_proxy.header.X-Authentik-Uid}"]}}}],"match":[{"not":[{"vars":{"{http.reverse_proxy.header.X-Authentik-Uid}":[""]}}]}]},{"handle":[{"handler":"headers","request":{"delete":["X-Authentik-Username"]}}]},{"handle":[{"handler":"headers","request":{"set":{"X-Authentik-Username":["{http.reverse_proxy.header.X-Authentik-Username}"]}}}],"match":[{"not":[{"vars":{"{http.reverse_proxy.header.X-Authentik-Username}":[""]}}]}]}]}],"handler":"reverse_proxy","headers":{"request":{"set":{"X-Forwarded-Method":["{http.request.method}"],"X-Forwarded-Uri":["{http.request.uri}"]}}},"rewrite":{"method":"GET","uri":"/outpost.goauthentik.io/auth/caddy"},"upstreams":[{"dial":"authentik-server:9000"}]},{"handler":"reverse_proxy","upstreams":[{"dial":"portainer:9000"}]}]}]}]}]}],"match":[{"host":["portainer.indehoven.com"]}],"terminal":true},{"handle":[{"handler":"subroute","routes":[{"handle":[{"handler":"subroute","routes":[{"handle":[{"handler":"crowdsec"},{"handler":"appsec"}]},{"handle":[{"handler":"reverse_proxy","upstreams":[{"dial":"authentik-server:9000"}]}],"match":[{"path":["/outpost.goauthentik.io/*"]}]},{"handle":[{"handle_response":[{"match":{"status_code":[2]},"routes":[{"handle":[{"handler":"vars"}]},{"handle":[{"handler":"headers","request":{"delete":["X-Authentik-Email"]}}]},{"handle":[{"handler":"headers","request":{"set":{"X-Authentik-Email":["{http.reverse_proxy.header.X-Authentik-Email}"]}}}],"match":[{"not":[{"vars":{"{http.reverse_proxy.header.X-Authentik-Email}":[""]}}]}]},{"handle":[{"handler":"headers","request":{"delete":["X-Authentik-Groups"]}}]},{"handle":[{"handler":"headers","request":{"set":{"X-Authentik-Groups":["{http.reverse_proxy.header.X-Authentik-Groups}"]}}}],"match":[{"not":[{"vars":{"{http.reverse_proxy.header.X-Authentik-Groups}":[""]}}]}]},{"handle":[{"handler":"headers","request":{"delete":["X-Authentik-Jwt"]}}]},{"handle":[{"handler":"headers","request":{"set":{"X-Authentik-Jwt":["{http.reverse_proxy.header.X-Authentik-Jwt}"]}}}],"match":[{"not":[{"vars":{"{http.reverse_proxy.header.X-Authentik-Jwt}":[""]}}]}]},{"handle":[{"handler":"headers","request":{"delete":["X-Authentik-Name"]}}]},{"handle":[{"handler":"headers","request":{"set":{"X-Authentik-Name":["{http.reverse_proxy.header.X-Authentik-Name}"]}}}],"match":[{"not":[{"vars":{"{http.reverse_proxy.header.X-Authentik-Name}":[""]}}]}]},{"handle":[{"handler":"headers","request":{"delete":["X-Authentik-Uid"]}}]},{"handle":[{"handler":"headers","request":{"set":{"X-Authentik-Uid":["{http.reverse_proxy.header.X-Authentik-Uid}"]}}}],"match":[{"not":[{"vars":{"{http.reverse_proxy.header.X-Authentik-Uid}":[""]}}]}]},{"handle":[{"handler":"headers","request":{"delete":["X-Authentik-Username"]}}]},{"handle":[{"handler":"headers","request":{"set":{"X-Authentik-Username":["{http.reverse_proxy.header.X-Authentik-Username}"]}}}],"match":[{"not":[{"vars":{"{http.reverse_proxy.header.X-Authentik-Username}":[""]}}]}]}]}],"handler":"reverse_proxy","headers":{"request":{"set":{"X-Forwarded-Method":["{http.request.method}"],"X-Forwarded-Uri":["{http.request.uri}"]}}},"rewrite":{"method":"GET","uri":"/outpost.goauthentik.io/auth/caddy"},"upstreams":[{"dial":"authentik-server:9000"}]},{"handler":"reverse_proxy","upstreams":[{"dial":"dockhand:3000"}]}]}]}]}]}],"match":[{"host":["dockhand.indehoven.com"]}],"terminal":true},{"handle":[{"handler":"subroute","routes":[{"handle":[{"handler":"subroute","routes":[{"handle":[{"handler":"crowdsec"},{"handler":"appsec"}]},{"handle":[{"handler":"reverse_proxy","upstreams":[{"dial":"authentik-server:9000"}]}],"match":[{"path":["/outpost.goauthentik.io/*"]}]},{"handle":[{"handle_response":[{"match":{"status_code":[2]},"routes":[{"handle":[{"handler":"vars"}]},{"handle":[{"handler":"headers","request":{"delete":["X-Authentik-Email"]}}]},{"handle":[{"handler":"headers","request":{"set":{"X-Authentik-Email":["{http.reverse_proxy.header.X-Authentik-Email}"]}}}],"match":[{"not":[{"vars":{"{http.reverse_proxy.header.X-Authentik-Email}":[""]}}]}]},{"handle":[{"handler":"headers","request":{"delete":["X-Authentik-Groups"]}}]},{"handle":[{"handler":"headers","request":{"set":{"X-Authentik-Groups":["{http.reverse_proxy.header.X-Authentik-Groups}"]}}}],"match":[{"not":[{"vars":{"{http.reverse_proxy.header.X-Authentik-Groups}":[""]}}]}]},{"handle":[{"handler":"headers","request":{"delete":["X-Authentik-Jwt"]}}]},{"handle":[{"handler":"headers","request":{"set":{"X-Authentik-Jwt":["{http.reverse_proxy.header.X-Authentik-Jwt}"]}}}],"match":[{"not":[{"vars":{"{http.reverse_proxy.header.X-Authentik-Jwt}":[""]}}]}]},{"handle":[{"handler":"headers","request":{"delete":["X-Authentik-Name"]}}]},{"handle":[{"handler":"headers","request":{"set":{"X-Authentik-Name":["{http.reverse_proxy.header.X-Authentik-Name}"]}}}],"match":[{"not":[{"vars":{"{http.reverse_proxy.header.X-Authentik-Name}":[""]}}]}]},{"handle":[{"handler":"headers","request":{"delete":["X-Authentik-Uid"]}}]},{"handle":[{"handler":"headers","request":{"set":{"X-Authentik-Uid":["{http.reverse_proxy.header.X-Authentik-Uid}"]}}}],"match":[{"not":[{"vars":{"{http.reverse_proxy.header.X-Authentik-Uid}":[""]}}]}]},{"handle":[{"handler":"headers","request":{"delete":["X-Authentik-Username"]}}]},{"handle":[{"handler":"headers","request":{"set":{"X-Authentik-Username":["{http.reverse_proxy.header.X-Authentik-Username}"]}}}],"match":[{"not":[{"vars":{"{http.reverse_proxy.header.X-Authentik-Username}":[""]}}]}]}]}],"handler":"reverse_proxy","headers":{"request":{"set":{"X-Forwarded-Method":["{http.request.method}"],"X-Forwarded-Uri":["{http.request.uri}"]}}},"rewrite":{"method":"GET","uri":"/outpost.goauthentik.io/auth/caddy"},"upstreams":[{"dial":"authentik-server:9000"}]},{"handler":"reverse_proxy","upstreams":[{"dial":"zerobyte:4096"}]}]}]}]}]}],"match":[{"host":["zerobyte.indehoven.com"]}],"terminal":true},{"handle":[{"handler":"subroute","routes":[{"handle":[{"handler":"subroute","routes":[{"handle":[{"handler":"crowdsec"},{"handler":"appsec"}]},{"handle":[{"handler":"reverse_proxy","upstreams":[{"dial":"authentik-server:9000"}]}],"match":[{"path":["/outpost.goauthentik.io/*"]}]},{"handle":[{"handle_response":[{"match":{"status_code":[2]},"routes":[{"handle":[{"handler":"vars"}]},{"handle":[{"handler":"headers","request":{"delete":["X-Authentik-Email"]}}]},{"handle":[{"handler":"headers","request":{"set":{"X-Authentik-Email":["{http.reverse_proxy.header.X-Authentik-Email}"]}}}],"match":[{"not":[{"vars":{"{http.reverse_proxy.header.X-Authentik-Email}":[""]}}]}]},{"handle":[{"handler":"headers","request":{"delete":["X-Authentik-Groups"]}}]},{"handle":[{"handler":"headers","request":{"set":{"X-Authentik-Groups":["{http.reverse_proxy.header.X-Authentik-Groups}"]}}}],"match":[{"not":[{"vars":{"{http.reverse_proxy.header.X-Authentik-Groups}":[""]}}]}]},{"handle":[{"handler":"headers","request":{"delete":["X-Authentik-Jwt"]}}]},{"handle":[{"handler":"headers","request":{"set":{"X-Authentik-Jwt":["{http.reverse_proxy.header.X-Authentik-Jwt}"]}}}],"match":[{"not":[{"vars":{"{http.reverse_proxy.header.X-Authentik-Jwt}":[""]}}]}]},{"handle":[{"handler":"headers","request":{"delete":["X-Authentik-Name"]}}]},{"handle":[{"handler":"headers","request":{"set":{"X-Authentik-Name":["{http.reverse_proxy.header.X-Authentik-Name}"]}}}],"match":[{"not":[{"vars":{"{http.reverse_proxy.header.X-Authentik-Name}":[""]}}]}]},{"handle":[{"handler":"headers","request":{"delete":["X-Authentik-Uid"]}}]},{"handle":[{"handler":"headers","request":{"set":{"X-Authentik-Uid":["{http.reverse_proxy.header.X-Authentik-Uid}"]}}}],"match":[{"not":[{"vars":{"{http.reverse_proxy.header.X-Authentik-Uid}":[""]}}]}]},{"handle":[{"handler":"headers","request":{"delete":["X-Authentik-Username"]}}]},{"handle":[{"handler":"headers","request":{"set":{"X-Authentik-Username":["{http.reverse_proxy.header.X-Authentik-Username}"]}}}],"match":[{"not":[{"vars":{"{http.reverse_proxy.header.X-Authentik-Username}":[""]}}]}]}]}],"handler":"reverse_proxy","headers":{"request":{"set":{"X-Forwarded-Method":["{http.request.method}"],"X-Forwarded-Uri":["{http.request.uri}"]}}},"rewrite":{"method":"GET","uri":"/outpost.goauthentik.io/auth/caddy"},"upstreams":[{"dial":"authentik-server:9000"}]},{"handler":"reverse_proxy","upstreams":[{"dial":"uptime-kuma:3001"}]}]}]}]}]}],"match":[{"host":["monitor.indehoven.com"]}],"terminal":true},{"handle":[{"handler":"subroute","routes":[{"handle":[{"handler":"subroute","routes":[{"handle":[{"handler":"crowdsec"},{"handler":"appsec"}]},{"handle":[{"handler":"reverse_proxy","upstreams":[{"dial":"authentik-server:9000"}]}],"match":[{"path":["/outpost.goauthentik.io/*"]}]},{"handle":[{"handle_response":[{"match":{"status_code":[2]},"routes":[{"handle":[{"handler":"vars"}]},{"handle":[{"handler":"headers","request":{"delete":["X-Authentik-Email"]}}]},{"handle":[{"handler":"headers","request":{"set":{"X-Authentik-Email":["{http.reverse_proxy.header.X-Authentik-Email}"]}}}],"match":[{"not":[{"vars":{"{http.reverse_proxy.header.X-Authentik-Email}":[""]}}]}]},{"handle":[{"handler":"headers","request":{"delete":["X-Authentik-Groups"]}}]},{"handle":[{"handler":"headers","request":{"set":{"X-Authentik-Groups":["{http.reverse_proxy.header.X-Authentik-Groups}"]}}}],"match":[{"not":[{"vars":{"{http.reverse_proxy.header.X-Authentik-Groups}":[""]}}]}]},{"handle":[{"handler":"headers","request":{"delete":["X-Authentik-Jwt"]}}]},{"handle":[{"handler":"headers","request":{"set":{"X-Authentik-Jwt":["{http.reverse_proxy.header.X-Authentik-Jwt}"]}}}],"match":[{"not":[{"vars":{"{http.reverse_proxy.header.X-Authentik-Jwt}":[""]}}]}]},{"handle":[{"handler":"headers","request":{"delete":["X-Authentik-Name"]}}]},{"handle":[{"handler":"headers","request":{"set":{"X-Authentik-Name":["{http.reverse_proxy.header.X-Authentik-Name}"]}}}],"match":[{"not":[{"vars":{"{http.reverse_proxy.header.X-Authentik-Name}":[""]}}]}]},{"handle":[{"handler":"headers","request":{"delete":["X-Authentik-Uid"]}}]},{"handle":[{"handler":"headers","request":{"set":{"X-Authentik-Uid":["{http.reverse_proxy.header.X-Authentik-Uid}"]}}}],"match":[{"not":[{"vars":{"{http.reverse_proxy.header.X-Authentik-Uid}":[""]}}]}]},{"handle":[{"handler":"headers","request":{"delete":["X-Authentik-Username"]}}]},{"handle":[{"handler":"headers","request":{"set":{"X-Authentik-Username":["{http.reverse_proxy.header.X-Authentik-Username}"]}}}],"match":[{"not":[{"vars":{"{http.reverse_proxy.header.X-Authentik-Username}":[""]}}]}]}]}],"handler":"reverse_proxy","headers":{"request":{"set":{"X-Forwarded-Method":["{http.request.method}"],"X-Forwarded-Uri":["{http.request.uri}"]}}},"rewrite":{"method":"GET","uri":"/outpost.goauthentik.io/auth/caddy"},"upstreams":[{"dial":"authentik-server:9000"}]},{"handler":"reverse_proxy","upstreams":[{"dial":"dozzle:8080"}]}]}]}]}]}],"match":[{"host":["dozzle.indehoven.com"]}],"terminal":true},{"handle":[{"handler":"subroute","routes":[{"handle":[{"handler":"subroute","routes":[{"handle":[{"handler":"crowdsec"},{"handler":"appsec"}]},{"handle":[{"handler":"reverse_proxy","upstreams":[{"dial":"authentik-server:9000"}]}],"match":[{"path":["/outpost.goauthentik.io/*"]}]},{"handle":[{"handle_response":[{"match":{"status_code":[2]},"routes":[{"handle":[{"handler":"vars"}]},{"handle":[{"handler":"headers","request":{"delete":["X-Authentik-Email"]}}]},{"handle":[{"handler":"headers","request":{"set":{"X-Authentik-Email":["{http.reverse_proxy.header.X-Authentik-Email}"]}}}],"match":[{"not":[{"vars":{"{http.reverse_proxy.header.X-Authentik-Email}":[""]}}]}]},{"handle":[{"handler":"headers","request":{"delete":["X-Authentik-Groups"]}}]},{"handle":[{"handler":"headers","request":{"set":{"X-Authentik-Groups":["{http.reverse_proxy.header.X-Authentik-Groups}"]}}}],"match":[{"not":[{"vars":{"{http.reverse_proxy.header.X-Authentik-Groups}":[""]}}]}]},{"handle":[{"handler":"headers","request":{"delete":["X-Authentik-Jwt"]}}]},{"handle":[{"handler":"headers","request":{"set":{"X-Authentik-Jwt":["{http.reverse_proxy.header.X-Authentik-Jwt}"]}}}],"match":[{"not":[{"vars":{"{http.reverse_proxy.header.X-Authentik-Jwt}":[""]}}]}]},{"handle":[{"handler":"headers","request":{"delete":["X-Authentik-Name"]}}]},{"handle":[{"handler":"headers","request":{"set":{"X-Authentik-Name":["{http.reverse_proxy.header.X-Authentik-Name}"]}}}],"match":[{"not":[{"vars":{"{http.reverse_proxy.header.X-Authentik-Name}":[""]}}]}]},{"handle":[{"handler":"headers","request":{"delete":["X-Authentik-Uid"]}}]},{"handle":[{"handler":"headers","request":{"set":{"X-Authentik-Uid":["{http.reverse_proxy.header.X-Authentik-Uid}"]}}}],"match":[{"not":[{"vars":{"{http.reverse_proxy.header.X-Authentik-Uid}":[""]}}]}]},{"handle":[{"handler":"headers","request":{"delete":["X-Authentik-Username"]}}]},{"handle":[{"handler":"headers","request":{"set":{"X-Authentik-Username":["{http.reverse_proxy.header.X-Authentik-Username}"]}}}],"match":[{"not":[{"vars":{"{http.reverse_proxy.header.X-Authentik-Username}":[""]}}]}]}]}],"handler":"reverse_proxy","headers":{"request":{"set":{"X-Forwarded-Method":["{http.request.method}"],"X-Forwarded-Uri":["{http.request.uri}"]}}},"rewrite":{"method":"GET","uri":"/outpost.goauthentik.io/auth/caddy"},"upstreams":[{"dial":"authentik-server:9000"}]},{"handler":"reverse_proxy","upstreams":[{"dial":"dns-server:5380"}]}]}]}]}]}],"match":[{"host":["dns.indehoven.com"]}],"terminal":true},{"handle":[{"handler":"subroute","routes":[{"handle":[{"handler":"subroute","routes":[{"handle":[{"handler":"crowdsec"},{"handler":"appsec"},{"handler":"reverse_proxy","upstreams":[{"dial":"authentik-server:9000"}]}]}]}]}]}],"match":[{"host":["id.indehoven.com"]}],"terminal":true},{"handle":[{"handler":"subroute","routes":[{"handle":[{"handler":"vars","root":"/data/www/indehoven.com"},{"encodings":{"gzip":{},"zstd":{}},"handler":"encode","prefer":["zstd","gzip"]}]},{"handle":[{"handler":"static_response","status_code":404}],"match":[{"not":[{"path":["/.well-known/*"]}],"path":["*/.*"]}]},{"handle":[{"handler":"static_response","headers":{"Location":["{http.request.orig_uri.path}/{http.request.orig_uri.prefixed_query}"]},"status_code":308}],"match":[{"file":{"try_files":["{http.request.uri.path}/index.php"]},"not":[{"path":["*/"]}]}]},{"handle":[{"handler":"rewrite","uri":"{http.matchers.file.relative}"}],"match":[{"file":{"split_path":[".php"],"try_files":["{http.request.uri.path}","{http.request.uri.path}/index.php","index.php"],"try_policy":"first_exist_fallback"}}]},{"handle":[{"handler":"reverse_proxy","transport":{"protocol":"fastcgi","split_path":[".php"]},"upstreams":[{"dial":"php-fpm:9000"}]}],"match":[{"path":["*.php"]}]},{"handle":[{"handler":"file_server","hide":["./Caddyfile"]}]}]}],"match":[{"host":["*.indehoven.com","indehoven.com"]}],"terminal":true},{"handle":[{"handler":"subroute","routes":[{"handle":[{"handler":"vars","root":"/data/www/bitsonline.nl"},{"encodings":{"gzip":{},"zstd":{}},"handler":"encode","prefer":["zstd","gzip"]}]},{"handle":[{"handler":"static_response","status_code":404}],"match":[{"not":[{"path":["/.well-known/*"]}],"path":["*/.*"]}]},{"handle":[{"handler":"static_response","headers":{"Location":["{http.request.orig_uri.path}/{http.request.orig_uri.prefixed_query}"]},"status_code":308}],"match":[{"file":{"try_files":["{http.request.uri.path}/index.php"]},"not":[{"path":["*/"]}]}]},{"handle":[{"handler":"rewrite","uri":"{http.matchers.file.relative}"}],"match":[{"file":{"split_path":[".php"],"try_files":["{http.request.uri.path}","{http.request.uri.path}/index.php","index.php"],"try_policy":"first_exist_fallback"}}]},{"handle":[{"handler":"reverse_proxy","transport":{"protocol":"fastcgi","split_path":[".php"]},"upstreams":[{"dial":"php-fpm:9000"}]}],"match":[{"path":["*.php"]}]},{"handle":[{"handler":"file_server","hide":["./Caddyfile"]}]}]}],"match":[{"host":["*.bitsonline","bitsonline.nl"]}],"terminal":true}],"trusted_proxies":{"source":"cloudflare"}},"srv1":{"client_ip_headers":["X-Forwarded-For","X-Real-IP"],"listen":[":80"],"routes":[{"handle":[{"handler":"subroute","routes":[{"handle":[{"handler":"static_response","headers":{"Location":["https://indehoven.com{http.request.uri}"]},"status_code":301}]}]}],"match":[{"host":["213.10.233.165"]}],"terminal":true}],"trusted_proxies":{"source":"cloudflare"}}}},"tls":{"automation":{"policies":[{"issuers":[{"email":"caddy@indehoven.com","module":"acme"},{"ca":"https://acme.zerossl.com/v2/DV90","email":"caddy@indehoven.com","module":"acme"}],"subjects":["vaultwarden.indehoven.com","aliasvault.indehoven.com","portainer.indehoven.com","dockhand.indehoven.com","zerobyte.indehoven.com","monitor.indehoven.com","dozzle.indehoven.com","dns.indehoven.com","id.indehoven.com"]},{"issuers":[{"challenges":{"dns":{"provider":{"api_token":"{env.CF_API_TOKEN}","name":"cloudflare"},"resolvers":["1.1.1.1"]}},"email":"caddy@indehoven.com","module":"acme"}],"subjects":["*.indehoven.com","indehoven.com","*.bitsonline","bitsonline.nl"]}]}}},"logging":{"logs":{"default":{"encoder":{"format":"json"},"exclude":["http.log.access.log0","http.log.access.log1","http.log.access.log10","http.log.access.log2","http.log.access.log3","http.log.access.log4","http.log.access.log5","http.log.access.log6","http.log.access.log7","http.log.access.log8","http.log.access.log9"],"level":"INFO","writer":{"filename":"/var/log/caddy/caddy.log","output":"file","roll_at":["00:00"],"roll_keep":5,"roll_keep_days":30,"roll_size_mb":954}},"log0":{"encoder":{"format":"json"},"include":["http.log.access.log0"],"level":"INFO","writer":{"filename":"/var/log/caddy/bitsonline.log","output":"file","roll_at":["00:00"],"roll_keep":5,"roll_keep_days":30,"roll_size_mb":954}},"log1":{"encoder":{"format":"json"},"include":["http.log.access.log1"],"level":"INFO","writer":{"filename":"/var/log/caddy/indehoven.log","output":"file","roll_at":["00:00"],"roll_keep":5,"roll_keep_days":30,"roll_size_mb":954}},"log10":{"encoder":{"format":"json"},"include":["http.log.access.log10"],"level":"INFO","writer":{"filename":"/var/log/caddy/zerobyte.log","output":"file","roll_at":["00:00"],"roll_keep":5,"roll_keep_days":30,"roll_size_mb":954}},"log2":{"encoder":{"format":"json"},"include":["http.log.access.log2"],"level":"INFO","writer":{"filename":"/var/log/caddy/aliasvault.log","output":"file","roll_at":["00:00"],"roll_keep":5,"roll_keep_days":30,"roll_size_mb":954}},"log3":{"encoder":{"format":"json"},"include":["http.log.access.log3"],"level":"INFO","writer":{"filename":"/var/log/caddy/id.log","output":"file","roll_at":["00:00"],"roll_keep":5,"roll_keep_days":30,"roll_size_mb":954}},"log4":{"encoder":{"format":"json"},"include":["http.log.access.log4"],"level":"INFO","writer":{"filename":"/var/log/caddy/uptime-kuma.log","output":"file","roll_at":["00:00"],"roll_keep":5,"roll_keep_days":30,"roll_size_mb":954}},"log5":{"encoder":{"format":"json"},"include":["http.log.access.log5"],"level":"INFO","writer":{"filename":"/var/log/caddy/dns.log","output":"file","roll_at":["00:00"],"roll_keep":5,"roll_keep_days":30,"roll_size_mb":954}},"log6":{"encoder":{"format":"json"},"include":["http.log.access.log6"],"level":"INFO","writer":{"filename":"/var/log/caddy/dockhand.log","output":"file","roll_at":["00:00"],"roll_keep":5,"roll_keep_days":30,"roll_size_mb":954}},"log7":{"encoder":{"format":"json"},"include":["http.log.access.log7"],"level":"INFO","writer":{"filename":"/var/log/caddy/dozzle.log","output":"file","roll_at":["00:00"],"roll_keep":5,"roll_keep_days":30,"roll_size_mb":954}},"log8":{"encoder":{"format":"json"},"include":["http.log.access.log8"],"level":"INFO","writer":{"filename":"/var/log/caddy/portainer.log","output":"file","roll_at":["00:00"],"roll_keep":5,"roll_keep_days":30,"roll_size_mb":954}},"log9":{"encoder":{"format":"json"},"include":["http.log.access.log9"],"level":"INFO","writer":{"filename":"/var/log/caddy/vaultwarden.log","output":"file","roll_at":["00:00"],"roll_keep":5,"roll_keep_days":30,"roll_size_mb":954}}}}}